pytornis/__init__.py
pytornis/pytornis.py
pytornis-0.0.1.dist-info/METADATA
pytornis-0.0.1.dist-info/WHEEL
pytornis-0.0.1.dist-info/top_level.txt
pytornis-0.0.1.dist-info/RECORD
