Metadata-Version: 2.4
Name: pytornis
Version: 0.0.1
Summary: Industrial Deep Learning framework with CPU/GPU support, tensors, autograd, and CUDA kernels
Author-email: Luis Fernando Montaño Hernández <tu_email@example.com>
License: MIT
Keywords: deep-learning,tensor,cuda,cpu,autograd,AI,industrial
Classifier: Programming Language :: Python :: 3
Classifier: License :: OSI Approved :: MIT License
Classifier: Operating System :: OS Independent
Requires-Python: >=3.10
Provides-Extra: dev
Requires-Dist: pytest; extra == "dev"
Requires-Dist: mypy; extra == "dev"
Provides-Extra: cuda
Requires-Dist: pycuda; extra == "cuda"
Provides-Extra: clang
Requires-Dist: clang; extra == "clang"
